README
setup.py
djoosh/__init__.py
djoosh/loading.py
djoosh/mixins.py
djoosh/models.py
djoosh/signals.py
djoosh/urls.py
djoosh/utils.py
djoosh/view.py
djoosh.egg-info/PKG-INFO
djoosh.egg-info/SOURCES.txt
djoosh.egg-info/dependency_links.txt
djoosh.egg-info/top_level.txt