Metadata-Version: 1.0
Name: djoosh
Version: 0.1
Summary: A super simple Django-whoosh search engine 
Home-page: http://packages.python.org/djoosh
Author: Alex Berezovskiy
Author-email: letoosh@gmail.com
License: BSD
Keywords: django whoosh search models simple
Platform: UNKNOWN
Classifier: Development Status :: 3 - Alpha
Classifier: Topic :: Utilities
Classifier: License :: OSI Approved :: BSD License
